LICENSE
MANIFEST.in
README.md
setup.py
django_data_explorer/__init__.py
django_data_explorer/endpoint.py
django_data_explorer/filterform.py
django_data_explorer/map.py
django_data_explorer/table.py
django_data_explorer/widget.py
django_data_explorer.egg-info/PKG-INFO
django_data_explorer.egg-info/SOURCES.txt
django_data_explorer.egg-info/dependency_links.txt
django_data_explorer.egg-info/not-zip-safe
django_data_explorer.egg-info/requires.txt
django_data_explorer.egg-info/top_level.txt
django_data_explorer/static/django_data_explorer/dist/data-explorer-no-datatables.css
django_data_explorer/static/django_data_explorer/dist/data-explorer.css
django_data_explorer/static/django_data_explorer/dist/data-explorer.js
django_data_explorer/static/django_data_explorer/dist/data-explorer.js.map
django_data_explorer/static/django_data_explorer/dist/images/br_down.png
django_data_explorer/static/django_data_explorer/dist/images/layers-2x.png
django_data_explorer/static/django_data_explorer/dist/images/layers.png
django_data_explorer/static/django_data_explorer/dist/images/marker-icon-2x.png
django_data_explorer/static/django_data_explorer/dist/images/marker-icon.png
django_data_explorer/static/django_data_explorer/dist/images/marker-shadow.png
django_data_explorer/static/django_data_explorer/dist/images/sort_asc.png
django_data_explorer/static/django_data_explorer/dist/images/sort_asc_disabled.png
django_data_explorer/static/django_data_explorer/dist/images/sort_both.png
django_data_explorer/static/django_data_explorer/dist/images/sort_desc.png
django_data_explorer/static/django_data_explorer/dist/images/sort_desc_disabled.png
django_data_explorer/templates/django_data_explorer/css_assets.html
django_data_explorer/templates/django_data_explorer/datatable_template.html
django_data_explorer/templates/django_data_explorer/filterform_template.html
django_data_explorer/templates/django_data_explorer/js_assets.html
django_data_explorer/templates/django_data_explorer/map_widget.html
django_data_explorer/templates/django_data_explorer/table_widget.html