Metadata-Version: 1.1
Name: django-data-explorer
Version: 0.2.0
Summary: AJAX tables and maps made simple
Home-page: http://github.com/qedsoftware/django-data-explorer
Author: Quantitative Engineering Design Inc.
Author-email: djangoqb@qed.ai
License: UNKNOWN
Platform: UNKNOWN
Classifier: Environment :: Web Environment
Classifier: Intended Audience :: Developers
Classifier: License :: OSI Approved :: BSD License
Classifier: Operating System :: OS Independent
Classifier: Programming Language :: Python
Classifier: Programming Language :: Python :: 2.7
Classifier: Programming Language :: Python :: 3
Classifier: Programming Language :: Python :: 3.2
Classifier: Programming Language :: Python :: 3.3
Classifier: Programming Language :: Python :: 3.4
Classifier: Programming Language :: Python :: 3.5
Classifier: Framework :: Django
